gena_selector/__init__.py
gena_selector/main.py
gena_selector-0.1.0.dist-info/WHEEL
gena_selector-0.1.0.dist-info/METADATA
gena_selector-0.1.0.dist-info/RECORD
